README.txt
setup.py
httpcachepurger/__init__.py
httpcachepurger/cmdline.py
httpcachepurger/purger.py
httpcachepurger.egg-info/PKG-INFO
httpcachepurger.egg-info/SOURCES.txt
httpcachepurger.egg-info/dependency_links.txt
httpcachepurger.egg-info/entry_points.txt
httpcachepurger.egg-info/top_level.txt