Metadata-Version: 1.1
Name: httpcachepurger
Version: 0.2.0
Summary: HTTP Cache purger client library
Home-page: https://code.asidev.net/projects/httpcachepurger
Author: Giacomo Bagnoli
Author-email: info@asidev.com
License: LICENSE.txt
Platform: UNKNOWN
Classifier: Development Status :: 3 - Alpha
Classifier: Intended Audience :: Developers
Classifier: License :: Other/Proprietary License
Classifier: Operating System :: OS Independent
Classifier: Programming Language :: Python
Classifier: Topic :: Internet :: WWW/HTTP
Classifier: Topic :: Software Development :: Libraries :: Python Modules
Classifier: Topic :: Utilities
